README.md
setup.cfg
setup.py
distributions_ZHM/Binomialdistribution.py
distributions_ZHM/Gaussiandistribution.py
distributions_ZHM/Generaldistribution.py
distributions_ZHM/__init__.py
distributions_ZHM.egg-info/PKG-INFO
distributions_ZHM.egg-info/SOURCES.txt
distributions_ZHM.egg-info/dependency_links.txt
distributions_ZHM.egg-info/not-zip-safe
distributions_ZHM.egg-info/top_level.txt